{"data":{"user":{"name":"Battseren B.","bio":"\" Coffee☕ to code converting machine🤖 \"\r\n- Tsee","isHireable":false,"avatarUrl":"https://avatars.githubusercontent.com/u/55880054?u=75ef894a4aa218b20879fdbb615f44aa4cebec3a&v=4","location":"Ulaanbaatar, Mongolia","pinnedItems":{"totalCount":2,"edges":[{"node":{"name":"mongolian-bank-exchange-rate","description":"Монгол банкуудын ханш - Exchange rates of Mongolian banks","forkCount":2,"stargazers":{"totalCount":7},"url":"https://github.com/btseee/mongolian-bank-exchange-rate","id":"R_kgDOHsbmZQ","diskUsage":25,"primaryLanguage":{"name":"Python","color":"#3572A5"}}},{"node":{"name":"excel-2-vcf-converter","description":"Excel contact list to VCF converter","forkCount":1,"stargazers":{"totalCount":0},"url":"https://github.com/monlogistics-group/excel-2-vcf-converter","id":"R_kgDOHh3OMQ","diskUsage":8,"primaryLanguage":{"name":"HTML","color":"#e34c26"}}}]}}}}